BiGLasso_Methods/DNNLasso.py
BiGLasso_Methods/GLasso.py
BiGLasso_Methods/TeraLasso.py
BiGLasso_Methods/__init__.py
BiGLasso_Methods/add_one.py
BiGLasso_Methods/DNNLasso/.git
BiGLasso_Methods/DNNLasso/DNNLasso.m
BiGLasso_Methods/DNNLasso/LICENSE
BiGLasso_Methods/DNNLasso/README.md
BiGLasso_Methods/DNNLasso/Readme.txt
BiGLasso_Methods/DNNLasso/test_coil100.m
BiGLasso_Methods/DNNLasso/test_synthetic.m
BiGLasso_Methods/DNNLasso/data/coil/coil100.png
BiGLasso_Methods/DNNLasso/data/coil/coil100_100_0.mat
BiGLasso_Methods/DNNLasso/data/coil/coil100_100_10.mat
BiGLasso_Methods/DNNLasso/data/coil/coil100_100_100.mat
BiGLasso_Methods/DNNLasso/data/coil/coil100_100_105.mat
BiGLasso_Methods/DNNLasso/data/coil/coil100_100_110.mat
BiGLasso_Methods/DNNLasso/data/coil/coil100_100_115.mat
BiGLasso_Methods/DNNLasso/data/coil/coil100_100_120.mat
BiGLasso_Methods/DNNLasso/data/coil/coil100_100_125.mat
BiGLasso_Methods/DNNLasso/data/coil/coil100_100_130.mat
BiGLasso_Methods/DNNLasso/data/coil/coil100_100_135.mat
BiGLasso_Methods/DNNLasso/data/coil/coil100_100_140.mat
BiGLasso_Methods/DNNLasso/data/coil/coil100_100_145.mat
BiGLasso_Methods/DNNLasso/data/coil/coil100_100_15.mat
BiGLasso_Methods/DNNLasso/data/coil/coil100_100_150.mat
BiGLasso_Methods/DNNLasso/data/coil/coil100_100_155.mat
BiGLasso_Methods/DNNLasso/data/coil/coil100_100_160.mat
BiGLasso_Methods/DNNLasso/data/coil/coil100_100_165.mat
BiGLasso_Methods/DNNLasso/data/coil/coil100_100_170.mat
BiGLasso_Methods/DNNLasso/data/coil/coil100_100_175.mat
BiGLasso_Methods/DNNLasso/data/coil/coil100_100_180.mat
BiGLasso_Methods/DNNLasso/data/coil/coil100_100_185.mat
BiGLasso_Methods/DNNLasso/data/coil/coil100_100_190.mat
BiGLasso_Methods/DNNLasso/data/coil/coil100_100_195.mat
BiGLasso_Methods/DNNLasso/data/coil/coil100_100_20.mat
BiGLasso_Methods/DNNLasso/data/coil/coil100_100_200.mat
BiGLasso_Methods/DNNLasso/data/coil/coil100_100_205.mat
BiGLasso_Methods/DNNLasso/data/coil/coil100_100_210.mat
biglasso_methods-1.0.2.dist-info/METADATA
biglasso_methods-1.0.2.dist-info/WHEEL
biglasso_methods-1.0.2.dist-info/licenses/LICENSE
biglasso_methods-1.0.2.dist-info/RECORD
