Metadata-Version: 2.4
Name: BiGLasso-Methods
Version: 1.0.2
Summary: An Python wrapper for Matlab-based bigraphical methods.
Project-URL: Homepage, https://github.com/BaileyAndrew/BiGLasso-Methods
Project-URL: Bug Tracker, https://github.com/BaileyAndrew/BiGLasso-Methods/issues
Author-email: Bailey Andrew <sceba@leeds.ac.uk>
License:                     GNU GENERAL PUBLIC LICENSE
License-File: LICENSE
Classifier: License :: OSI Approved :: MIT License
Classifier: Operating System :: OS Independent
Classifier: Programming Language :: Python :: 3
Classifier: Programming Language :: Python :: 3.9
Classifier: Programming Language :: Python :: 3.10
Classifier: Programming Language :: Python :: 3.11
Requires-Python: <3.12,>=3.9
Requires-Dist: gmgm
Requires-Dist: matlabengine
Requires-Dist: scikit-learn
